playpi/__init__.py
playpi/__main__.py
playpi/__version__.py
playpi/cli.py
playpi/config.py
playpi/example_prompts.py
playpi/exceptions.py
playpi/html.py
playpi/session.py
playpi/providers/__init__.py
playpi/providers/google/__init__.py
playpi/providers/google/auth.py
playpi/providers/google/cli_helpers.py
playpi/providers/google/gemini.py
playpi-1.0.12.dist-info/METADATA
playpi-1.0.12.dist-info/WHEEL
playpi-1.0.12.dist-info/entry_points.txt
playpi-1.0.12.dist-info/licenses/LICENSE
playpi-1.0.12.dist-info/RECORD
