Metadata-Version: 2.4
Name: playpi
Version: 1.0.12
Summary: Automate AI chat workflows through browser automation
Project-URL: Documentation, https://github.com/twardoch/playpi#readme
Project-URL: Issues, https://github.com/twardoch/playpi/issues
Project-URL: Source, https://github.com/twardoch/playpi
Author-email: Adam Twardoch <adam+github@twardoch.com>
License: MIT
License-File: LICENSE
Keywords: ai,automation,browser,chat,gemini,playwright
Classifier: Development Status :: 3 - Alpha
Classifier: Intended Audience :: Developers
Classifier: License :: OSI Approved :: MIT License
Classifier: Operating System :: OS Independent
Classifier: Programming Language :: Python
Classifier: Programming Language :: Python :: 3.12
Classifier: Programming Language :: Python :: Implementation :: CPython
Classifier: Topic :: Internet :: WWW/HTTP :: Browsers
Classifier: Topic :: Scientific/Engineering :: Artificial Intelligence
Classifier: Topic :: Software Development :: Libraries :: Python Modules
Requires-Python: >=3.12
Requires-Dist: fire>=0.5.0
Requires-Dist: html2text>=2020.1.16
Requires-Dist: loguru>=0.7.0
Requires-Dist: platformdirs>=3.0.0
Requires-Dist: playwright>=1.40.0
Requires-Dist: playwrightauthor>=1.0.13
Requires-Dist: pydantic>=2.0.0
Requires-Dist: rich>=13.0.0
Provides-Extra: all
Provides-Extra: dev
Requires-Dist: absolufy-imports>=0.3.1; extra == 'dev'
Requires-Dist: isort>=6.0.1; extra == 'dev'
Requires-Dist: mypy>=1.15.0; extra == 'dev'
Requires-Dist: pre-commit>=4.1.0; extra == 'dev'
Requires-Dist: pyupgrade>=3.19.1; extra == 'dev'
Requires-Dist: ruff>=0.9.7; extra == 'dev'
Provides-Extra: docs
Requires-Dist: myst-parser>=3.0.0; extra == 'docs'
Requires-Dist: sphinx-autodoc-typehints>=2.0.0; extra == 'docs'
Requires-Dist: sphinx-rtd-theme>=2.0.0; extra == 'docs'
Requires-Dist: sphinx>=7.2.6; extra == 'docs'
Provides-Extra: test
Requires-Dist: coverage[toml]>=7.6.12; extra == 'test'
Requires-Dist: pytest-asyncio>=0.25.3; extra == 'test'
Requires-Dist: pytest-benchmark[histogram]>=5.1.0; extra == 'test'
Requires-Dist: pytest-cov>=6.0.0; extra == 'test'
Requires-Dist: pytest-playwright>=0.4.0; extra == 'test'
Requires-Dist: pytest-xdist>=3.6.1; extra == 'test'
Requires-Dist: pytest>=8.3.4; extra == 'test'
